{
  "C_s": 172,
  "CFL_a": 0.2,
  "CFL_v": 0.2,
  "alpha": 0.2,
  "dim": 3,
  "block_size": 512,
  "box_length": [ 1.0, 1.0, 1.0 ],
  "box_margin_coefficient": [ 0.3, 0.3, 0.3 ],
  "cubic_factor_coefficient1D1": 2.0,
  "cubic_factor_coefficient1D2": 3.0,
  "cubic_factor_coefficient2D1": 10.0,
  "cubic_factor_coefficient2D2": 7.0,
  "cubic_factor_coefficient3D1": 1.0,
  "cubic_factor_coefficient3D2": 1.0,
  "eta": 0.5,
  "f_air": 0.0001,
  "gamma": 7.0,
  "gravity": -9.8,
  "gravity_coefficient": 10.0,
  "grid_size": 4096,
  "h_coefficient": 1.0,
  "kappa": 0.0001,
  "mass": 0.004,
  "particle_dim": [ 20, 20, 20 ],
  "particle_radius": 0.01,
  "poly6_factor_coefficient1": 315.0,
  "poly6_factor_coefficient2": 64.0,
  "rho_0": 1000.0,
  "spiky_grad_factor_coefficient": -45.0,
  "step_each_frame": 1,
  "time_delta": 0.0001,
  "time_delta_coefficient": 4,
  "velo_draw_max": 15.0,
  "velo_draw_min": 0.0,
  "velo_init_max": [ 0.01, -0.01, 0.01 ],
  "velo_init_min": [ -0.01, -0.02, -0.01 ],
  "vis_lapla_factor_coefficient": 45.0,
  "zone_dim": [ 25, 25, 25 ]
}
